disjrnet/__init__.py
disjrnet/main.py
disjrnet/base/__init__.py
disjrnet/base/base_data_loader.py
disjrnet/base/base_model.py
disjrnet/model/__init__.py
disjrnet/model/lightning_module.py
disjrnet/model/loss.py
disjrnet/model/metric.py
disjrnet/model/models.py
disjrnet_pytorch-0.1.2.dist-info/METADATA
disjrnet_pytorch-0.1.2.dist-info/WHEEL
disjrnet_pytorch-0.1.2.dist-info/top_level.txt
disjrnet_pytorch-0.1.2.dist-info/RECORD
