Metadata-Version: 2.1
Name: disjrnet-pytorch
Version: 0.1.2
Summary: A small example package
Home-page: https://github.com/youhs4554/disjrnet-pytorch.git
Author: hossay
Author-email: youhs4554@gmail.com
License: UNKNOWN
Download-URL: https://github.com/youhs4554/disjrnet-pytorch/archive/refs/tags/v0.1.1.tar.gz
Keywords: representation learning,weakly supervised learning,fall detection
Platform: UNKNOWN
Classifier: Programming Language :: Python :: 3
Classifier: Programming Language :: Python :: 3.6
Classifier: Programming Language :: Python :: 3.7
Classifier: Topic :: Scientific/Engineering :: Artificial Intelligence
Classifier: Topic :: Software Development :: Libraries :: Python Modules
Requires-Python: >=3.6
Requires-Dist: torch
Requires-Dist: torchvision
